qnshare/__init__.py
qnshare/cli.py
qnshare/client.py
qnshare/config.py
qnshare/exceptions.py
qnshare/interactive.py
qnshare/py.typed
qnshare/qn.py
qnshare/utils.py
qnshare-0.1.0.dist-info/WHEEL
qnshare-0.1.0.dist-info/entry_points.txt
qnshare-0.1.0.dist-info/METADATA
qnshare-0.1.0.dist-info/RECORD
