Metadata-Version: 2.3
Name: qnshare
Version: 0.1.0
Summary: 七牛云文件共享工具 - 一个简单易用的七牛云存储命令行工具
Keywords: qiniu,cloud,storage,file-sharing,cli
Author: wmymz
Author-email: wmymz <wmymz@icloud.com>
Classifier: Development Status :: 4 - Beta
Classifier: Intended Audience :: Developers
Classifier: License :: OSI Approved :: MIT License
Classifier: Programming Language :: Python :: 3
Classifier: Programming Language :: Python :: 3.8
Classifier: Programming Language :: Python :: 3.9
Classifier: Programming Language :: Python :: 3.10
Classifier: Programming Language :: Python :: 3.11
Classifier: Programming Language :: Python :: 3.12
Classifier: Topic :: Internet :: File Transfer Protocol (FTP)
Classifier: Topic :: System :: Archiving
Classifier: Topic :: Utilities
Requires-Dist: qiniu>=7.17.0
Requires-Dist: click>=8.0.0
Requires-Python: >=3.8
Project-URL: Homepage, https://github.com/qy527145/qnshare
Project-URL: Issues, https://github.com/qy527145/qnshare/issues
Project-URL: Repository, https://github.com/qy527145/qnshare
